{"/":{"bundle.aba81.css":{"type":"style","weight":1},"bundle.31597.esm.js":{"type":"script","weight":1},"route-home.chunk.7259b.esm.js":{"type":"script","weight":0.9},"route-home.chunk.c35a0.css":{"type":"style","weight":0.9}},"/notfound":{"bundle.aba81.css":{"type":"style","weight":1},"bundle.31597.esm.js":{"type":"script","weight":1},"route-notfound.chunk.6813f.esm.js":{"type":"script","weight":0.9},"route-notfound.chunk.5c189.css":{"type":"style","weight":0.9}},"/sign":{"bundle.aba81.css":{"type":"style","weight":1},"bundle.31597.esm.js":{"type":"script","weight":1},"route-sign.chunk.e5e20.esm.js":{"type":"script","weight":0.9},"route-sign.chunk.85ff4.css":{"type":"style","weight":0.9}}}